[
    {
        "title": "2017 Texas Renaissance Festival",
        "time": "9 AM",
        "address": "21778 FM 1774 Todd Mission, TX 77363 United States",
        "mapurl": "https://www.google.com/maps/place/Texas+Renaissance+Festival/@30.255949,-95.829653,15z/data=!4m2!3m1!1s0x0:0xa6d534b39703c1fa?sa=X&ved=0ahUKEwjV6L3kheHWAhUCa1AKHVCRCQoQ_BIIfDAN",
        "body": "The Texas Renaissance Festival, the nation’s largest, most acclaimed renaissance theme park, returns for the 43rd season with the addition of a ninth weekend. The magic of the Festival transports patrons to the 16th century offering enchanting experiences featuring world-renowned live entertainment, works by master artists and craftspeople, award winning food and drink, hand-powered rides and games, and over 100 interactive characters.",
        "link": "https://www.texrenfest.com/"
    },
    {
        "title": "Pearland Arts & Crafts on the Pavilion at Pearland Town Center",
        "time": "10 AM - 5 PM",
        "address": "11200 Broadway St Pearland, TX 77584 United States",
        "mapurl": "https://www.google.com/maps/place/11200+Broadway+St,+Pearland,+TX+77584/@29.5529446,-95.396428,17z/data=!3m1!4b1!4m5!3m4!1s0x8640933278c19b2b:0x5a7eff06ba60dee6!8m2!3d29.5529446!4d-95.3942393?hl=en",
        "body": "Experience a 2-day juried art show that will feature a variety of fine art and unique works for sale at the Pearland Arts & Crafts on the Pavilion. Spend the day outdoors strolling through the aisle filled with art while enjoying a food trucks court, sipping wine at their wine bistro, taking the little ones to the kids’ interactive station, and watching live performances. Admission: Free.",
        "link": "http://www.pearlandtowncenter.com/event/blt798c29e644482ddb"
    },
    {
        "title": "6th Annual King’s Oktoberfest Weekend at King’s Biergarten in Pearland",
        "time": "12 PM - 9 AM",
        "address": "1329 E Broadway Street Pearland, TX 77581 United States",
        "mapurl": "https://www.google.com/maps/place/Kings+Biergarten+%26+Restaurant/@29.5450175,-95.2290005,17z/data=!4m13!1m7!3m6!1s0x86409a8029e604e1:0x287c128b255d0d5!2s1329+E+Broadway+St,+Pearland,+TX+77581!3b1!8m2!3d29.5450175!4d-95.2268118!3m4!1s0x86409a81b68079ed:0xe027c68ee9ef6109!8m2!3d29.5450744!4d-95.2252606?hl=en",
        "body": "King’s annual Oktoberfest celebration returns with more live German music, more biers, more brats, and more fun. Admission starts at $12.",
        "link": "http://www.kingsoktoberfest.com/"
    },
    {
        "title": "EaDo Vintage Fest: One Year Anniversary Party",
        "time": "12 PM - 8 PM",
        "address": "4009 Polk St C, Houston , TX 77023 United States",
        "mapurl": "https://www.google.com/maps/place/EaDo+Vintage/@29.7403051,-95.3414416,17z/data=!4m13!1m7!3m6!1s0x8640beefcc4b4053:0x27872b24c19bd4d!2s4009+Polk+St,+Houston,+TX+77023!3b1!8m2!3d29.7403051!4d-95.3392529!3m4!1s0x8640be8dab34153d:0xd83eda2f7f81cb82!8m2!3d29.7403051!4d-95.339253?hl=en",
        "body": "Shop for vintage clothing, locally made products, artisans, food and more while vibing to DJs and live music at the EaDo Vintage Fest. Admission No cover.",
        "link": "https://www.facebook.com/events/164420347450458/"
    },
    {
        "title": "Roots Reggae Houston Music Festival at Hobby Event Center",
        "time": "12 PM - 10 PM",
        "address": "9906 Gulf Freeway Houston , TX 77034 United States",
        "mapurl": "https://www.google.com/maps/place/Hobby+Event+Center/@29.6494486,-95.2525064,17z/data=!4m13!1m7!3m6!1s0x864097a34f2c1e15:0x3979878d2ab9e1bf!2s9906+Gulf+Fwy,+Houston,+TX+77034!3b1!8m2!3d29.6494486!4d-95.2503177!3m4!1s0x864097a327299b2d:0xf65a01a9f3838576!8m2!3d29.6494486!4d-95.2503177?hl=en",
        "body": "Experience positive vibes, arts and crafts vendors, food and lots of reggae music at the Roots Reggae Houston Festival at the Hobby Event Center. Admission Tickets are $10. ",
        "link": "http://rootsreggaehouston.com/"
    },
    {
        "title": "Woodlands BBQ Festival at Town Green Park",
        "time": "1 PM - 5 PM",
        "address": "2099 Lake Robbins Dr. The Woodlands, TX 77380 United States",
        "mapurl": "https://www.google.com/maps/place/Town+Green+Park/@30.1623302,-95.4686636,17z/data=!4m13!1m7!3m6!1s0x864736c7c2587ca7:0xef68d5073e4aca21!2s2099+Lake+Robbins+Dr,+The+Woodlands,+TX+77380!3b1!8m2!3d30.1623302!4d-95.4664749!3m4!1s0x864736c7ecf83a75:0x74ab9e3242e683d0!8m2!3d30.1619179!4d-95.4661869?hl=en",
        "body": "The 2nd Annual Woodlands BBQ Festival will feature celebrated BBQ pitmasters from the Houston area. Enjoy an afternoon filled with the finest BBQ around, activities for the kids, live music, cold beer and the chance to bring awareness to Pulmonary Hypertension Association. Admission Tickets are $37.50; $75 for VIP.",
        "link": "https://tix.extremetix.com/webtix/4502"
    },
    {
        "title": "Houston Astros: Postseason Watch Parties at Minute Maid Park",
        "time": "1:30 PM",
        "address": "501 Crawford St Houston, TX 77002 United States",
        "mapurl": "https://www.google.com/maps/place/Minute+Maid+Park/@29.7577058,-95.3567286,17z/data=!4m13!1m7!3m6!1s0x8640bf2427efe3dd:0x3cdbc2df39563260!2sMinute+Maid+Park,+501+Crawford+St,+Houston,+TX+77002!3b1!8m2!3d29.7577058!4d-95.3545399!3m4!1s0x8640bf26db794291:0x81457f66271a17e1!8m2!3d29.7572684!4d-95.3555185?hl=en",
        "body": "For all the games in Boston and throughout the postseason, you’ll be able to join with up to 40,000 fans at the place the ‘Stros call home. Minute Maid Park will be hosting fans with the game on the big screen, live music, food trucks, and plenty to do for kids (face painting, inflatables, and games highlight the festivities). Free to attend, but attendees need to claim a free voucher in order to get in.",
        "link": "http://m.mlb.com/astros/tickets/postseason/festivities"
    },
    {
        "title": "Miami Vice Sunday Funday at Henke & Pillot Houston",
        "time": "3 PM",
        "address": "809 Congress Avenue Houston, TX 77002 United States",
        "mapurl": "https://www.google.com/maps?f=q&source=s_q&hl=en&geocode&q=809+Congress+Avenue+Houston+TX+77002+United+States",
        "body": "Spend your Sunday Funday having drinks and brunch as DJ Johnny Mac spins Miami style beats at Henke & Pillot Houston. Admission No cover.",
        "link": "https://www.facebook.com/events/1588651467823728/"
    },
    {
        "title": "Poetry Special: The Secret’s Out at The Secret Group",
        "time": "6 PM - 10 PM",
        "address": "2101 Polk Street Houston, TX 77003 United States",
        "mapurl": "https://www.google.com/maps/place/The+Secret+Group/@29.7489221,-95.3588784,17z/data=!4m13!1m7!3m6!1s0x8640bf1f4903992f:0x1df37b24cf60ec39!2s2101+Polk+St,+Houston,+TX+77003!3b1!8m2!3d29.7489221!4d-95.3566897!3m4!1s0x8640bf1f487a39f7:0x3074ecbd75c65a60!8m2!3d29.7489221!4d-95.3566897?hl=en",
        "body": "Hear poetry performances from 7 local poets and jam out to music from DJs at The Secret Group. Admission Tickets are $5 in advance and $10 at the door.",
        "link": "https://www.facebook.com/events/108860323123197/"
    },
    {
        "title": "The Black Angels in Concert at House of Blues",
        "time": "7 PM",
        "address": "1204 Caroline St. Houston, TX 77002 United States",
        "mapurl": "https://www.google.com/maps/place/House+of+Blues+Houston/@29.7539291,-95.3662451,17z/data=!3m1!5s0x8640bf3cee2a2c95:0x64dca85307fd6e90!4m13!1m7!3m6!1s0x8640bf3cebd10095:0x723e815154274f8d!2s1204+Caroline+St,+Houston,+TX+77002!3b1!8m2!3d29.7539291!4d-95.3640564!3m4!1s0x8640bf3cebd10095:0x878ee26dfabf0dd1!8m2!3d29.753846!4d-95.363937?hl=en",
        "body": "Austin-based psychedelic rock band, The Black Angels perform at House of Blues with openers Car Seat Headrest. Admission  Tickets start at $25.",
        "link": "https://www.facebook.com/HOBHouston"
    },
    {
        "title": "James Vincent McMorrow at The Heights Theater",
        "time": "7 PM",
        "address": "339 W 19th St Houston, TX 70008 United States",
        "mapurl": "https://www.google.com/maps/place/The+Heights+Theater/@29.8031919,-95.4050573,17z/data=!4m13!1m7!3m6!1s0x8640c7650a0b2a9f:0xe6ebe46a07659b49!2s339+W+19th+St,+Houston,+TX+77008!3b1!8m2!3d29.8031919!4d-95.4028686!3m4!1s0x8640c765a09f3fd5:0x984b90c41122f1ac!8m2!3d29.803166!4d-95.402878?hl=en",
        "body": "Irish artist and musician James Vincent McMorrow hits the stage to perform songs off of his new record We Move at The Heights Theater. Admission Tickets are $20.",
        "link": "https://prekindle.com/promo/id/24898849166435354"
    },
    {
        "title": "Houston Texans vs. Kansas City Chiefs at NRG Stadium",
        "time": "7:30 PM",
        "address": "Reliant Pkwy Houston, TX 77054 United States",
        "mapurl": "https://www.google.com/maps/place/NRG+Stadium/@29.6841758,-95.4123108,16z/data=!4m8!1m2!2m1!1sReliant+Pkwy+Houston+TX+77054+United+States!3m4!1s0x8640c0194b406bad:0x1b0f6ec2399a9d57!8m2!3d29.6847219!4d-95.4107074?hl=en",
        "body": "Cheer loud for the Texans as they battle it out against the Kansas City Chiefs at NRG Stadium. Admission Tickets range from $50 to $400.",
        "link": "http://www.houstontexans.com/team/season-schedule.html"
    },
    {
        "title": "Comic Chris Tucker at Smart Financial Centre",
        "time": "8 PM",
        "address": "18111 Lexington Boulevard Sugar Land, TX 77479 United States",
        "mapurl": "https://www.google.com/maps/place/Smart+Financial+Centre+at+Sugar+Land/@29.5770582,-95.6454815,17z/data=!4m13!1m7!3m6!1s0x8640e6aa9d6bcc0f:0x3cd081a29ac177e8!2s18111+Lexington+Blvd,+Sugar+Land,+TX+77479!3b1!8m2!3d29.5770582!4d-95.6432928!3m4!1s0x8640e6aa864523d5:0xa1176fe18dfecc2b!8m2!3d29.577058!4d-95.643293?hl=en",
        "body": "Bust a gut laughing when comedian and actor Chris Tucker makes his way to the Smart Financial Centre at Sugar Land. The show was rescheduled from Wednesday, September 9, 2017 following Hurricane Harvey. Admission Tickets start at $45.50.",
        "link": "http://www.smartfinancialcentre.net/"
    },
    {
        "title": "Songwriter Sundays at Dean’s Downtown",
        "time": "9 PM",
        "address": "316 Main St Houston, TX United States",
        "mapurl": "https://www.google.com/maps/place/Dean's/@29.7618501,-95.363591,17z/data=!4m13!1m7!3m6!1s0x8640bf2c0cd61bad:0xd7b9b963693a5a29!2s316+Main+St,+Houston,+TX+77002!3b1!8m2!3d29.7618501!4d-95.3614023!3m4!1s0x8640bf2ff4d71471:0x3fe98dbc7f5297ac!8m2!3d29.7618501!4d-95.3614023?hl=en",
        "body": "Spend your Sunday relaxing and listening to music by local singer songwriters at Dean's Downtown. ",
        "link": "https://www.facebook.com/events/277162696115991/"
    }
]